impactEffects/__init__.py
impactEffects-0.0.1.dist-info/LICENSE
impactEffects-0.0.1.dist-info/METADATA
impactEffects-0.0.1.dist-info/WHEEL
impactEffects-0.0.1.dist-info/top_level.txt
impactEffects-0.0.1.dist-info/RECORD
